{
  "version": 1,
  "updatedAt": "2026-06-15T18:25:37Z",
  "brand": "Alleral",
  "tagline": "Roblox scripts that stay updated without babysitting.",
  "loaderVersion": "8.2.25",
  "coreVersion": "2.9.5",
  "uiLibrary": "Syde",
  "uiVersion": "4.0.1-syde",
  "sydePatch": 36,
  "announcement": "",
  "loadstring": "loadstring(game:HttpGet(\"https://raw.githubusercontent.com/evanbackup1256-ship-it/kick/main/hub/bootstrap.luau?t=\" .. tick(), true))()",
  "repo": "evanbackup1256-ship-it/kick",
  "branch": "main",
  "features": [
    "Finds the right script when you inject",
    "Syde UI with live status on each game",
    "Site and scripts pull from GitHub automatically",
    "Game status comes from real inject data, not guesses",
    "Updates land within about a minute of a push",
    "Live executor compatibility via WEAO — every major exploit tracked"
  ],
  "faq": [
    {
      "q": "How do I open the site?",
      "a": "Any browser works - phone or PC. Grab the link from Share and bookmark it if you want. You don't need a Roblox account just to browse. Roblox and an executor only matter when you run the loadstring."
    },
    {
      "q": "How do I load Alleral?",
      "a": "Copy the bootstrap loadstring from the homepage once, save it in your executor, and run it in a supported game. It always pulls the latest loader and scripts from GitHub — you never replace the saved script after updates."
    },
    {
      "q": "Which games are supported?",
      "a": "Check the Games tab - status updates live. Scripts only load when a game is marked Working or Testing."
    },
    {
      "q": "Why didn't the script load?",
      "a": "Usually it's the wrong game, a weak executor, or the game is marked Broken/Maintenance."
    },
    {
      "q": "Does it auto-update?",
      "a": "Yeah. The loader checks GitHub every ~45 seconds and reloads when something new is pushed."
    },
    {
      "q": "How do I report a bug?",
      "a": "Use the Support section below. Reports go straight to Discord."
    }
  ],
  "changelog": [
    {
      "date": "2026-06-12",
      "title": "Loader 8.2.24 — core fix + hub live tracker",
      "items": [
        "Fix alleral_ui validation (Syde patch 18 sync) — Core failed on inject",
        "Hub website revamp with real-time live status dashboard (15s refresh)",
        "New public /api/live/status endpoint for versions, sync, and inject health"
      ]
    },
    {
      "date": "2026-06-12",
      "title": "Loader 8.2.23 — version lock + relay fixes",
      "items": [
        "Bootstrap v1.0.3 — commit-pinned loader only; rejects version/commit/syde patch mismatch",
        "Loader syncs SYDE_PATCH + RELEASE_FALLBACK from release.json; exact syde patch required",
        "Fix telemetry_feed retention SQL and admin telemetry endpoints when auto_sync is unavailable"
      ]
    },
    {
      "date": "2026-06-12",
      "title": "Syde patch 18 — fix empty UI / toggle keybind crash",
      "items": [
        "Loader 8.2.22 · Syde patch 18 — stop renaming Render subtree (ToggleConfiguration KeyBind.Title)",
        "Fixes blank hub with no tabs when a toggle uses keybind configuration"
      ]
    },
    {
      "date": "2026-06-12",
      "title": "Telemetry v3.3 — richer Discord + admin feed",
      "items": [
        "Loader 8.2.21 · telemetry 3.3 — place update events, bootstrap/commit/build context on every payload",
        "Errors now include stack trace, recent session actions, place build, and longer detail text",
        "Admin Stats tab shows 48h inject/error/update counts plus a live telemetry feed"
      ]
    },
    {
      "date": "2026-06-12",
      "title": "Loader 8.2.20 — commit sync, game update notice, legacy purge",
      "items": [
        "Loader 8.2.20 — bump_release always mirrors RELEASE_FALLBACK.commit from release.json",
        "Bootstrap v1.0.2 warns when PlaceVersion changed; script still loads normally",
        "Bootstrap purges legacy v3/v4 loaders and obfuscated UI dumps from executor workspace"
      ]
    },
    {
      "date": "2026-06-12",
      "title": "Loader 8.2.19 — register limit fix + commit-pinned bootstrap",
      "items": [
        "Loader 8.2.19 — teleport/relaunch hooks moved to hub/loader_relaunch.luau to stay under Luau register cap",
        "Bootstrap v1.0.1 fetches cfg/release.json first and pins loader.luau to the release commit",
        "Bootstrap rejects stale CDN copies when loader version does not match release.json"
      ]
    },
    {
      "date": "2026-06-12",
      "title": "Eternal bootstrap loadstring + Syde patch v17",
      "items": [
        "Loader 8.2.18 — save the bootstrap loadstring once; updates pull from GitHub automatically",
        "Workspace cache purged each reload so stale hub/loader files never run",
        "Syde patch v17 — silent logging, Render template fix, compat-only Alleral layer"
      ]
    },
    {
      "date": "2026-06-12",
      "title": "Syde UI (upstream + compat fixes)",
      "items": [
        "Loader 8.2.16 ships essencejs Syde with a thin Alleral compat layer (patch v15)",
        "Dropdown, modal, template casing, and Volt asset sanitization fixes kept",
        "Syde fetch uses jsDelivr commit mirror + in-memory cache when workspace write fails"
      ]
    },
    {
      "date": "2026-06-12",
      "title": "Maclib UI integration",
      "items": [
        "Loader 8.2.0 replaces custom hub/ui stack with Maclib 1.2.6",
        "Removed Neverlose, WindUI, Fusion, OnyxUI vendor bootstrap modules",
        "Core 2.9.0 keeps existing game script UI API via Maclib adapters"
      ]
    },
    {
      "date": "2026-06-11",
      "title": "WindUI revamp",
      "items": [
        "Replaced Obsidian with WindUI across all game scripts",
        "Alleral green accent on the open button and dark theme default",
        "Same script API — toggles, sliders, dropdowns, and live status panels"
      ]
    },
    {
      "date": "2026-06-11",
      "title": "Ban API rework",
      "items": [
        "Ban by Roblox username (resolves to UserId server-side)",
        "Cascade across UserId, username, HWID, and fingerprint",
        "Ban check now sends placeId and universeId from the game",
        "Hub layout refresh + game thumbnails"
      ]
    },
    {
      "date": "2026-06-11",
      "title": "Public hub went live",
      "items": [
        "Turnstile gate on first visit",
        "Share section with copyable links",
        "Live/Offline indicator in the nav",
        "Bug reports from the site"
      ]
    },
    {
      "date": "2026-06-10",
      "title": "Obsidian UI",
      "items": [
        "Dropped Rayfield for Obsidian",
        "Manifest-driven script list",
        "Loader auto-update bumped to v7.2"
      ]
    }
  ],
  "bugCategories": [
    "Script Crash",
    "UI Bug",
    "Game Not Detected",
    "Feature Broken",
    "Executor Issue",
    "Other"
  ],
  "games": {
    "kick_a_lucky_block": {
      "placeIds": [89469502395769],
      "universeIds": [10004244222],
      "robloxUrl": "https://www.roblox.com/games/89469502395769",
      "description": "Kick automation, plot tools, live roll filters, and full economy loops.",
      "uiTabs": ["Kick", "Plot", "Events", "Inventory", "Tools", "Settings"],
      "scriptFeatures": [
        {
          "name": "Auto kick",
          "category": "Kick",
          "desc": "Runs to the pad, kicks, and resets when rolls don't match your filters."
        },
        {
          "name": "Roll filters",
          "category": "Kick",
          "desc": "Filter by rarity, weight, style, and favorite-only rolls."
        },
        {
          "name": "Humanize kicks",
          "category": "Kick",
          "desc": "Adds natural timing so kicks look less robotic."
        },
        {
          "name": "Show what's rolling",
          "category": "Kick",
          "desc": "Live overlay of the current roll while farming."
        },
        {
          "name": "Auto train",
          "category": "Plot",
          "desc": "Trains stats automatically on your plot."
        },
        {
          "name": "Train + collect",
          "category": "Plot",
          "desc": "Trains and grabs rewards in one loop."
        },
        {
          "name": "Auto place best",
          "category": "Plot",
          "desc": "Places your best blocks on the plot."
        },
        {
          "name": "Protect slots",
          "category": "Plot",
          "desc": "Keeps important plot slots from being overwritten."
        },
        {
          "name": "Auto upgrade pets",
          "category": "Plot",
          "desc": "Upgrades pets when you can afford it."
        },
        {
          "name": "Auto upgrade plot",
          "category": "Plot",
          "desc": "Buys plot upgrades on a schedule."
        },
        {
          "name": "Buy best weight",
          "category": "Economy",
          "desc": "Purchases the best weight upgrades automatically."
        },
        {
          "name": "Auto rebirth",
          "category": "Economy",
          "desc": "Rebirths when requirements are met."
        },
        {
          "name": "Favorite scanner",
          "category": "Inventory",
          "desc": "Scans backpack and favorites matching items."
        },
        {
          "name": "Battle automation",
          "category": "Events",
          "desc": "Auto battle, mastery, and weather event helpers."
        },
        {
          "name": "Discord webhooks",
          "category": "Tools",
          "desc": "Ping Discord when you hit rare rolls or milestones."
        },
        {
          "name": "Config profiles",
          "category": "Settings",
          "desc": "Save/load settings and quiet mode toggles."
        }
      ]
    },
    "speed_keyboard_escape": {
      "placeIds": [95082159892680],
      "robloxUrl": "https://www.roblox.com/games/95082159892680",
      "description": "Step farming, win routes, shop automation, and treadmill tweaks.",
      "uiTabs": ["Main", "Auto", "Shop", "Misc", "Settings"],
      "scriptFeatures": [
        {
          "name": "Step farm",
          "category": "Auto",
          "desc": "Hits the purple step popup for you."
        },
        {
          "name": "Win farm",
          "category": "Auto",
          "desc": "Picks a smart route and farms wins."
        },
        {
          "name": "Lock in place",
          "category": "Main",
          "desc": "Stops sliding on the treadmill."
        },
        {
          "name": "Auto rebirth",
          "category": "Main",
          "desc": "Rebirths when you can afford it."
        },
        {
          "name": "Equip best gear",
          "category": "Shop",
          "desc": "Keeps your best items equipped."
        },
        {
          "name": "Auto buy",
          "category": "Shop",
          "desc": "Buys whatever you picked in the shop list."
        },
        {
          "name": "Anti AFK",
          "category": "Misc",
          "desc": "Prevents idle kicks while farming."
        }
      ]
    },
    "slime_rng": {
      "placeIds": [92416421522960],
      "universeIds": [9792947201],
      "robloxUrl": "https://www.roblox.com/games/92416421522960",
      "description": "Slime rolls, crafting, pets, potions, and zone farming.",
      "uiTabs": ["Main", "Auto", "Inventory", "Misc", "Settings"],
      "scriptFeatures": [
        {
          "name": "Farm best zone",
          "category": "Auto",
          "desc": "Farms your best unlocked zone."
        },
        {
          "name": "Keep rolling",
          "category": "Auto",
          "desc": "Spins for slimes automatically."
        },
        {
          "name": "Equip best",
          "category": "Auto",
          "desc": "Swaps to your best slime by filter."
        },
        {
          "name": "Auto rebirth",
          "category": "Auto",
          "desc": "Rebirths when requirements are met."
        },
        {
          "name": "Unlock machines",
          "category": "Auto",
          "desc": "Opens crafting and XP transfer when affordable."
        },
        {
          "name": "Auto shoot",
          "category": "Combat",
          "desc": "Fires at enemies for you."
        },
        {
          "name": "Upgrade tree",
          "category": "Progression",
          "desc": "Buys the cheapest skill node it can."
        },
        {
          "name": "Auto craft",
          "category": "Inventory",
          "desc": "Trades slimes in for selected recipes."
        },
        {
          "name": "Collect loot",
          "category": "Inventory",
          "desc": "Snags drops that match your filter."
        },
        {
          "name": "Auto feed pets",
          "category": "Pets",
          "desc": "Feeds your selected slime + food combo."
        },
        {
          "name": "Auto potion",
          "category": "Pets",
          "desc": "Drinks potions from your list."
        },
        { "name": "Noclip", "category": "Misc", "desc": "Walk through walls." },
        {
          "name": "Freecam",
          "category": "Misc",
          "desc": "Fly the camera with WASD + Q/E."
        },
        {
          "name": "FPS boost",
          "category": "Misc",
          "desc": "Lowers graphics for smoother farming."
        }
      ]
    },
    "build_a_ring_farm": {
      "placeIds": [107646426076756],
      "robloxUrl": "https://www.roblox.com/games/107646426076756",
      "description": "Full farm automation — planting, upgrades, pets, events, and honey.",
      "uiTabs": [
        "Farm",
        "Seeds",
        "Upgrade",
        "Shop",
        "Events",
        "Pets",
        "Misc",
        "Settings"
      ],
      "scriptFeatures": [
        {
          "name": "Plant seeds",
          "category": "Farm",
          "desc": "Plants seeds from your bag onto empty plots."
        },
        {
          "name": "Clear plants",
          "category": "Farm",
          "desc": "Removes unwanted plants automatically."
        },
        {
          "name": "Upgrade plants",
          "category": "Farm",
          "desc": "Levels up what's already planted."
        },
        {
          "name": "Unlock plots",
          "category": "Farm",
          "desc": "Buys new plot slots when affordable."
        },
        {
          "name": "Expand farm",
          "category": "Farm",
          "desc": "Purchases the next farm expansion."
        },
        {
          "name": "Sell crates",
          "category": "Farm",
          "desc": "Walks over and sells held crates."
        },
        {
          "name": "Auto spray & fertilizer",
          "category": "Farm",
          "desc": "Keeps crops maintained on a loop."
        },
        {
          "name": "Roll & buy seeds",
          "category": "Seeds",
          "desc": "Rolls and buys seeds from the shop."
        },
        {
          "name": "Toss bad seeds",
          "category": "Seeds",
          "desc": "Discards seeds that don't match filters."
        },
        {
          "name": "Stat upgrades",
          "category": "Upgrade",
          "desc": "Auto-upgrades roll, luck, plot, saw, and sprinkler stats."
        },
        {
          "name": "Contracts",
          "category": "Shop",
          "desc": "Turns in and rerolls contracts."
        },
        {
          "name": "Event combat",
          "category": "Events",
          "desc": "Shoots event mobs and collects rush/alien drops."
        },
        {
          "name": "Honey farm",
          "category": "Events",
          "desc": "Runs honey minigame and rolls rewards."
        },
        {
          "name": "Pet optimizer",
          "category": "Pets",
          "desc": "Feeds, equips best pets, and sells extras."
        },
        { "name": "Fly", "category": "Misc", "desc": "Fly around the map." }
      ]
    },
    "survive_a_zombie_arena": {
      "placeIds": [114204398207377],
      "robloxUrl": "https://www.roblox.com/games/114204398207377",
      "description": "Zombie arena combat — kill aura, auto farm preset, ESP, and safe zones.",
      "uiTabs": ["Farm", "Combat", "Player", "Visual", "Misc", "Settings"],
      "scriptFeatures": [
        {
          "name": "Auto farm preset",
          "category": "Farm",
          "desc": "One toggle for kill aura, god mode, skip, shoot, loot, and safe zone."
        },
        {
          "name": "Auto skip wave",
          "category": "Farm",
          "desc": "Votes to skip waves automatically."
        },
        {
          "name": "Collect pickups",
          "category": "Farm",
          "desc": "Teleports to shards, minerals, and credit drops."
        },
        {
          "name": "Auto equip best gun",
          "category": "Farm",
          "desc": "Equips the strongest tool in your backpack."
        },
        {
          "name": "Auto upgrade & buy",
          "category": "Farm",
          "desc": "Probes upgrade and shop remotes for gear."
        },
        {
          "name": "Auto plant mine",
          "category": "Defense",
          "desc": "Places mines on cooldown."
        },
        {
          "name": "Kill aura",
          "category": "Combat",
          "desc": "Instant zombie damage aura."
        },
        {
          "name": "Instant kill",
          "category": "Combat",
          "desc": "Uses max damage per hit."
        },
        {
          "name": "Auto shoot",
          "category": "Combat",
          "desc": "Keeps your weapon firing."
        },
        {
          "name": "God mode",
          "category": "Combat",
          "desc": "Locks health at maximum."
        },
        {
          "name": "Aimbot",
          "category": "Combat",
          "desc": "Snaps camera to nearest zombie while shooting."
        },
        {
          "name": "Hitbox expander",
          "category": "Combat",
          "desc": "Enlarges zombie hitboxes."
        },
        {
          "name": "Fly & noclip",
          "category": "Player",
          "desc": "WASD flight and walk-through-walls."
        },
        {
          "name": "Teleport safe spot",
          "category": "Player",
          "desc": "Teleports to the classic safe corner."
        },
        {
          "name": "Zombie ESP",
          "category": "Visual",
          "desc": "Highlights zombies through walls."
        }
      ]
    }
  },
  "links": {
    "website": "https://alleral-telemetry-production.up.railway.app/",
    "mirror": "https://evanbackup1256-ship-it.github.io/kick/",
    "github": "https://github.com/evanbackup1256-ship-it/kick",
    "loaderRaw": "https://raw.githubusercontent.com/evanbackup1256-ship-it/kick/main/loader.luau",
    "relay": "https://alleral-telemetry-production.up.railway.app",
    "admin": "https://alleral-telemetry-production.up.railway.app/admin"
  },
  "executors": [],
  "resources": [
    {
      "title": "WEAO — Live executors",
      "desc": "WhatExpsAre.Online status feed (same data as Tools)",
      "url": "https://whatexpsare.online/",
      "icon": "pulse"
    },
    {
      "title": "Loader source",
      "desc": "Raw loader.luau on GitHub",
      "urlKey": "loaderRaw",
      "icon": "code"
    },
    {
      "title": "Repository",
      "desc": "Full project + game scripts",
      "urlKey": "github",
      "icon": "github"
    },
    {
      "title": "Sync status",
      "desc": "Live GitHub auto-sync JSON",
      "url": "/api/sync/status",
      "icon": "sync"
    },
    {
      "title": "Health check",
      "desc": "Relay uptime + commit hash",
      "url": "/health",
      "icon": "pulse"
    }
  ],
  "credits": {
    "headline": "Built by Sammy.",
    "subheadline": "Alleral — loader, hub, game scripts, and everything on this site.",
    "teams": [
      {
        "id": "creator",
        "title": "Creator",
        "members": [
          {
            "id": "sammy",
            "displayName": "Sammy",
            "role": "Owner & Developer",
            "robloxUsername": "ProgrammerSammy",
            "bio": "Everything you see here — loader architecture, telemetry relay, game scripts, and this hub.",
            "featured": true,
            "accent": "#2997ff",
            "tags": ["Loader", "Backend", "Hub", "Games"],
            "links": { "github": "https://github.com/evanbackup1256-ship-it" }
          }
        ]
      }
    ],
    "specialThanks": []
  }
}
